gestures4kivy/__init__.py
gestures4kivy/commongestures.py
gestures4kivy-0.1.3.dist-info/LICENSE
gestures4kivy-0.1.3.dist-info/METADATA
gestures4kivy-0.1.3.dist-info/WHEEL
gestures4kivy-0.1.3.dist-info/top_level.txt
gestures4kivy-0.1.3.dist-info/RECORD
